bentso/__init__.py
bentso/client.py
bentso/constants.py
bentso/db.py
bentso/filesystem.py
bentso/iterators.py
bentso-0.3.dist-info/LICENSE
bentso-0.3.dist-info/METADATA
bentso-0.3.dist-info/WHEEL
bentso-0.3.dist-info/top_level.txt
bentso-0.3.dist-info/RECORD
