Metadata-Version: 2.1
Name: bentso
Version: 0.3
Summary: BONSAI living model for European electricity via ENTSO-E API
Home-page: https://github.com/BONSAMURAIS/bentso
Author: Chris Mutel
Author-email: cmutel@gmail.com
License: BSD 3-Clause License
Requires-Dist: appdirs
Requires-Dist: beautifulsoup4
Requires-Dist: docopt
Requires-Dist: entsoe-py
Requires-Dist: pandas
Requires-Dist: peewee
Requires-Dist: pytz
Requires-Dist: requests
